IST411Team1/__init__.py
IST411Team1/__main__.py
IST411Team1/node1.py
IST411Team1/node2.py
IST411Team1/node3.py
IST411Team1/node4.py
IST411Team1/node5.py
IST411Team1/p2p.py
IST411Team1-1.0.1.dist-info/DESCRIPTION.rst
IST411Team1-1.0.1.dist-info/METADATA
IST411Team1-1.0.1.dist-info/RECORD
IST411Team1-1.0.1.dist-info/WHEEL
IST411Team1-1.0.1.dist-info/entry_points.txt
IST411Team1-1.0.1.dist-info/metadata.json
IST411Team1-1.0.1.dist-info/top_level.txt
